beancount_zenmoney/__init__.py
beancount_zenmoney/importer.py
beancount_zenmoney/py.typed
beancount_zenmoney-0.1.1a1.dist-info/WHEEL
beancount_zenmoney-0.1.1a1.dist-info/METADATA
beancount_zenmoney-0.1.1a1.dist-info/RECORD
