Metadata-Version: 2.4
Name: beancount-zenmoney
Version: 0.1.1a1
Summary: Beancount importer for Zenmoney exports
Keywords: beancount,beangulp,zenmoney,importer,accounting,finance
Author: Andrei Sviridov
License-Expression: MIT
Classifier: Development Status :: 3 - Alpha
Classifier: Intended Audience :: End Users/Desktop
Classifier: License :: OSI Approved :: MIT License
Classifier: Operating System :: OS Independent
Classifier: Programming Language :: Python :: 3
Classifier: Programming Language :: Python :: 3.10
Classifier: Programming Language :: Python :: 3.11
Classifier: Programming Language :: Python :: 3.12
Classifier: Programming Language :: Python :: 3.13
Classifier: Topic :: Office/Business :: Financial :: Accounting
Requires-Dist: beancount>=3.0.0
Requires-Dist: beangulp>=0.1.0
Requires-Python: >=3.10
Project-URL: Homepage, https://github.com/MrLokans/beancount-zenmoney
Project-URL: Issues, https://github.com/MrLokans/beancount-zenmoney/issues
Project-URL: Repository, https://github.com/MrLokans/beancount-zenmoney
